{
  "Anaganaga Oka Raju [2D | Telugu]": {
    "shows": 77,
    "gross": 586363.0,
    "sold": 3723,
    "totalSeats": 27128,
    "venues": 60,
    "cities": 13,
    "fastfilling": 3,
    "housefull": 0,
    "occupancy": 13.72
  },
  "Mayasabha - The Hall of Illusion [2D | Hindi]": {
    "shows": 55,
    "gross": 191987.0,
    "sold": 849,
    "totalSeats": 9892,
    "venues": 50,
    "cities": 16,
    "fastfilling": 2,
    "housefull": 1,
    "occupancy": 8.58
  },
  "Mana Shankara Vara Prasad Garu [2D | Telugu]": {
    "shows": 121,
    "gross": 1050303.0,
    "sold": 6809,
    "totalSeats": 50340,
    "venues": 89,
    "cities": 16,
    "fastfilling": 6,
    "housefull": 0,
    "occupancy": 13.53
  },
  "Avatar: Fire and Ash [3D | English]": {
    "shows": 7,
    "gross": 27420.0,
    "sold": 68,
    "totalSeats": 1422,
    "venues": 7,
    "cities": 6,
    "fastfilling": 1,
    "housefull": 0,
    "occupancy": 4.78
  },
  "Border 2 [2D | Hindi]": {
    "shows": 718,
    "gross": 4124422.98,
    "sold": 15288,
    "totalSeats": 165831,
    "venues": 240,
    "cities": 62,
    "fastfilling": 10,
    "housefull": 2,
    "occupancy": 9.22
  },
  "Nari Nari Naduma Murari [2D | Telugu]": {
    "shows": 90,
    "gross": 390723.0,
    "sold": 2456,
    "totalSeats": 29754,
    "venues": 66,
    "cities": 12,
    "fastfilling": 3,
    "housefull": 0,
    "occupancy": 8.25
  },
  "Mardaani 3 [2D | Hindi]": {
    "shows": 284,
    "gross": 2059129.0,
    "sold": 7939,
    "totalSeats": 61787,
    "venues": 157,
    "cities": 32,
    "fastfilling": 5,
    "housefull": 0,
    "occupancy": 12.85
  },
  "The Raja Saab [2D | Telugu]": {
    "shows": 20,
    "gross": 120707.0,
    "sold": 901,
    "totalSeats": 6822,
    "venues": 16,
    "cities": 5,
    "fastfilling": 0,
    "housefull": 0,
    "occupancy": 13.21
  },
  "Dhurandhar [2D | Hindi]": {
    "shows": 53,
    "gross": 270047.0,
    "sold": 1007,
    "totalSeats": 8804,
    "venues": 51,
    "cities": 13,
    "fastfilling": 1,
    "housefull": 0,
    "occupancy": 11.44
  },
  "Send Help [4DX 3D | English]": {
    "shows": 13,
    "gross": 61190.0,
    "sold": 136,
    "totalSeats": 1380,
    "venues": 13,
    "cities": 7,
    "fastfilling": 0,
    "housefull": 0,
    "occupancy": 9.86
  },
  "The Housemaid [2D | English]": {
    "shows": 9,
    "gross": 32670.0,
    "sold": 91,
    "totalSeats": 1101,
    "venues": 9,
    "cities": 5,
    "fastfilling": 0,
    "housefull": 0,
    "occupancy": 8.27
  },
  "Om Shanti Shanti Shantihi [2D | Telugu]": {
    "shows": 66,
    "gross": 402848.0,
    "sold": 3187,
    "totalSeats": 19608,
    "venues": 52,
    "cities": 10,
    "fastfilling": 2,
    "housefull": 0,
    "occupancy": 16.25
  },
  "Marty Supreme [2D | English]": {
    "shows": 29,
    "gross": 150223.0,
    "sold": 440,
    "totalSeats": 3970,
    "venues": 27,
    "cities": 8,
    "fastfilling": 0,
    "housefull": 0,
    "occupancy": 11.08
  },
  "Gandhi Talks [2D | Silent]": {
    "shows": 36,
    "gross": 78530.0,
    "sold": 342,
    "totalSeats": 7025,
    "venues": 31,
    "cities": 11,
    "fastfilling": 0,
    "housefull": 0,
    "occupancy": 4.87
  },
  "Bhartha Mahasayulaku Wignyapthi [2D | Telugu]": {
    "shows": 13,
    "gross": 42128.0,
    "sold": 261,
    "totalSeats": 2987,
    "venues": 10,
    "cities": 5,
    "fastfilling": 0,
    "housefull": 0,
    "occupancy": 8.74
  },
  "Mercy [3D | English]": {
    "shows": 6,
    "gross": 10190.0,
    "sold": 34,
    "totalSeats": 577,
    "venues": 6,
    "cities": 4,
    "fastfilling": 0,
    "housefull": 0,
    "occupancy": 5.89
  },
  "Send Help [2D | English]": {
    "shows": 21,
    "gross": 31290.0,
    "sold": 153,
    "totalSeats": 3026,
    "venues": 19,
    "cities": 6,
    "fastfilling": 0,
    "housefull": 0,
    "occupancy": 5.06
  },
  "Jagannath [2D | Telugu]": {
    "shows": 6,
    "gross": 12462.0,
    "sold": 61,
    "totalSeats": 1319,
    "venues": 6,
    "cities": 5,
    "fastfilling": 0,
    "housefull": 0,
    "occupancy": 4.62
  },
  "Zootopia 2 [2D | English]": {
    "shows": 3,
    "gross": 14230.0,
    "sold": 63,
    "totalSeats": 278,
    "venues": 3,
    "cities": 2,
    "fastfilling": 0,
    "housefull": 0,
    "occupancy": 22.66
  },
  "Shelter [2D | English]": {
    "shows": 37,
    "gross": 131235.0,
    "sold": 385,
    "totalSeats": 5091,
    "venues": 29,
    "cities": 9,
    "fastfilling": 0,
    "housefull": 0,
    "occupancy": 7.56
  },
  "Demon Slayer: Kimetsu no Yaiba Infinity Castle [2D | Japanese]": {
    "shows": 1,
    "gross": 2550.0,
    "sold": 17,
    "totalSeats": 54,
    "venues": 1,
    "cities": 1,
    "fastfilling": 0,
    "housefull": 0,
    "occupancy": 31.48
  },
  "Dhrutarashtrudu [2D | Telugu]": {
    "shows": 7,
    "gross": 6421.0,
    "sold": 66,
    "totalSeats": 1338,
    "venues": 6,
    "cities": 3,
    "fastfilling": 0,
    "housefull": 0,
    "occupancy": 4.93
  },
  "Send Help [3D | English]": {
    "shows": 49,
    "gross": 156874.0,
    "sold": 434,
    "totalSeats": 7810,
    "venues": 43,
    "cities": 12,
    "fastfilling": 2,
    "housefull": 0,
    "occupancy": 5.56
  },
  "Avatar: Fire and Ash [4DX 3D | English]": {
    "shows": 3,
    "gross": 27154.0,
    "sold": 67,
    "totalSeats": 320,
    "venues": 3,
    "cities": 3,
    "fastfilling": 0,
    "housefull": 0,
    "occupancy": 20.94
  },
  "Chatha Pacha: The Ring of Rowdies [2D | Telugu]": {
    "shows": 5,
    "gross": 2600.0,
    "sold": 13,
    "totalSeats": 1113,
    "venues": 5,
    "cities": 1,
    "fastfilling": 0,
    "housefull": 0,
    "occupancy": 1.17
  },
  "Prakambanam [2D | Malayalam]": {
    "shows": 35,
    "gross": 295610.0,
    "sold": 1645,
    "totalSeats": 7582,
    "venues": 23,
    "cities": 12,
    "fastfilling": 4,
    "housefull": 1,
    "occupancy": 21.7
  },
  "One/4 [2D | Telugu]": {
    "shows": 5,
    "gross": 23568.0,
    "sold": 191,
    "totalSeats": 1088,
    "venues": 5,
    "cities": 3,
    "fastfilling": 1,
    "housefull": 0,
    "occupancy": 17.56
  },
  "Devagudi [2D | Telugu]": {
    "shows": 14,
    "gross": 161902.0,
    "sold": 1466,
    "totalSeats": 4183,
    "venues": 11,
    "cities": 8,
    "fastfilling": 4,
    "housefull": 0,
    "occupancy": 35.05
  },
  "Zamana [2D | Telugu]": {
    "shows": 7,
    "gross": 99908.0,
    "sold": 823,
    "totalSeats": 3563,
    "venues": 6,
    "cities": 3,
    "fastfilling": 1,
    "housefull": 0,
    "occupancy": 23.1
  },
  "Tere Ishk Mein [2D | Hindi]": {
    "shows": 2,
    "gross": 0.0,
    "sold": 0,
    "totalSeats": 440,
    "venues": 1,
    "cities": 1,
    "fastfilling": 0,
    "housefull": 0,
    "occupancy": 0.0
  },
  "Valathu Vasathe Kallan [2D | Malayalam]": {
    "shows": 101,
    "gross": 708003.64,
    "sold": 3636,
    "totalSeats": 30691,
    "venues": 49,
    "cities": 17,
    "fastfilling": 1,
    "housefull": 0,
    "occupancy": 11.85
  },
  "Chatha Pacha: The Ring of Rowdies [2D | Malayalam]": {
    "shows": 63,
    "gross": 172746.78,
    "sold": 905,
    "totalSeats": 15586,
    "venues": 38,
    "cities": 14,
    "fastfilling": 0,
    "housefull": 0,
    "occupancy": 5.81
  },
  "Lockdown [2D | Tamil]": {
    "shows": 9,
    "gross": 11820.0,
    "sold": 88,
    "totalSeats": 2322,
    "venues": 6,
    "cities": 6,
    "fastfilling": 0,
    "housefull": 0,
    "occupancy": 3.79
  },
  "Hot Spot 2 Much [2D | Tamil]": {
    "shows": 10,
    "gross": 15420.0,
    "sold": 100,
    "totalSeats": 3491,
    "venues": 5,
    "cities": 3,
    "fastfilling": 0,
    "housefull": 0,
    "occupancy": 2.86
  },
  "Aga Aga Sunbai! Kay Mhantay Sasubai? [2D | Marathi]": {
    "shows": 38,
    "gross": 206123.0,
    "sold": 1032,
    "totalSeats": 6747,
    "venues": 35,
    "cities": 8,
    "fastfilling": 1,
    "housefull": 0,
    "occupancy": 15.3
  },
  "Baby Girl [2D | Malayalam]": {
    "shows": 29,
    "gross": 60126.0,
    "sold": 227,
    "totalSeats": 5454,
    "venues": 19,
    "cities": 8,
    "fastfilling": 0,
    "housefull": 0,
    "occupancy": 4.16
  },
  "Thalaivar Thambi Thalaimaiyil [2D | Tamil]": {
    "shows": 11,
    "gross": 31930.0,
    "sold": 225,
    "totalSeats": 3284,
    "venues": 7,
    "cities": 5,
    "fastfilling": 0,
    "housefull": 0,
    "occupancy": 6.85
  },
  "Christina [2D | Malayalam]": {
    "shows": 2,
    "gross": 6620.0,
    "sold": 37,
    "totalSeats": 334,
    "venues": 2,
    "cities": 1,
    "fastfilling": 0,
    "housefull": 0,
    "occupancy": 11.08
  },
  "Sarvam Maya [2D | Malayalam]": {
    "shows": 3,
    "gross": 6680.0,
    "sold": 38,
    "totalSeats": 433,
    "venues": 2,
    "cities": 2,
    "fastfilling": 0,
    "housefull": 0,
    "occupancy": 8.78
  },
  "Border 2 [IMAX 2D | Hindi]": {
    "shows": 30,
    "gross": 314460.0,
    "sold": 636,
    "totalSeats": 9145,
    "venues": 16,
    "cities": 7,
    "fastfilling": 0,
    "housefull": 0,
    "occupancy": 6.95
  },
  "Magic Mushrooms [2D | Malayalam]": {
    "shows": 3,
    "gross": 6840.0,
    "sold": 40,
    "totalSeats": 464,
    "venues": 3,
    "cities": 2,
    "fastfilling": 0,
    "housefull": 0,
    "occupancy": 8.62
  },
  "Karuppu Pulsar [2D | Tamil]": {
    "shows": 11,
    "gross": 39320.0,
    "sold": 286,
    "totalSeats": 3197,
    "venues": 7,
    "cities": 5,
    "fastfilling": 0,
    "housefull": 0,
    "occupancy": 8.95
  },
  "Mellisai [2D | Tamil]": {
    "shows": 1,
    "gross": 2700.0,
    "sold": 18,
    "totalSeats": 194,
    "venues": 1,
    "cities": 1,
    "fastfilling": 0,
    "housefull": 0,
    "occupancy": 9.28
  },
  "Sirai [2D | Tamil]": {
    "shows": 3,
    "gross": 4440.0,
    "sold": 39,
    "totalSeats": 644,
    "venues": 2,
    "cities": 2,
    "fastfilling": 0,
    "housefull": 0,
    "occupancy": 6.06
  },
  "Trimukha [2D | Telugu]": {
    "shows": 6,
    "gross": 3930.0,
    "sold": 39,
    "totalSeats": 2937,
    "venues": 4,
    "cities": 3,
    "fastfilling": 0,
    "housefull": 0,
    "occupancy": 1.33
  },
  "Paree: An Unsolved Mystery [2D | Odia]": {
    "shows": 1,
    "gross": 0.0,
    "sold": 0,
    "totalSeats": 68,
    "venues": 1,
    "cities": 1,
    "fastfilling": 0,
    "housefull": 0,
    "occupancy": 0.0
  },
  "Vijaynagar'er Hirey (Kakababu) [2D | Bengali]": {
    "shows": 3,
    "gross": 1080.0,
    "sold": 6,
    "totalSeats": 403,
    "venues": 3,
    "cities": 3,
    "fastfilling": 0,
    "housefull": 0,
    "occupancy": 1.49
  },
  "Jockey [2D | Tamil]": {
    "shows": 1,
    "gross": 0.0,
    "sold": 0,
    "totalSeats": 163,
    "venues": 1,
    "cities": 1,
    "fastfilling": 0,
    "housefull": 0,
    "occupancy": 0.0
  },
  "Mankatha [2D | Tamil]": {
    "shows": 7,
    "gross": 9920.0,
    "sold": 90,
    "totalSeats": 2111,
    "venues": 4,
    "cities": 4,
    "fastfilling": 0,
    "housefull": 0,
    "occupancy": 4.26
  },
  "Parasakthi [2D | Tamil]": {
    "shows": 3,
    "gross": 4100.0,
    "sold": 24,
    "totalSeats": 584,
    "venues": 2,
    "cities": 2,
    "fastfilling": 0,
    "housefull": 0,
    "occupancy": 4.11
  },
  "Thiraivi [2D | Tamil]": {
    "shows": 1,
    "gross": 0.0,
    "sold": 0,
    "totalSeats": 170,
    "venues": 1,
    "cities": 1,
    "fastfilling": 0,
    "housefull": 0,
    "occupancy": 0.0
  },
  "Chowkidar [2D | Kannada]": {
    "shows": 4,
    "gross": 4350.0,
    "sold": 24,
    "totalSeats": 1799,
    "venues": 3,
    "cities": 3,
    "fastfilling": 0,
    "housefull": 0,
    "occupancy": 1.33
  },
  "Kattemar [2D | Tulu]": {
    "shows": 4,
    "gross": 3000.0,
    "sold": 20,
    "totalSeats": 626,
    "venues": 2,
    "cities": 1,
    "fastfilling": 0,
    "housefull": 0,
    "occupancy": 3.19
  },
  "Hok Kolorob [2D | Bengali]": {
    "shows": 1,
    "gross": 1800.0,
    "sold": 10,
    "totalSeats": 198,
    "venues": 1,
    "cities": 1,
    "fastfilling": 0,
    "housefull": 0,
    "occupancy": 5.05
  },
  "Krantijyoti Vidyalay Marathi Madhyam [2D | Marathi]": {
    "shows": 49,
    "gross": 171606.0,
    "sold": 857,
    "totalSeats": 9516,
    "venues": 42,
    "cities": 6,
    "fastfilling": 1,
    "housefull": 0,
    "occupancy": 9.01
  },
  "Human Cocaine [2D | Hindi]": {
    "shows": 13,
    "gross": 75480.0,
    "sold": 274,
    "totalSeats": 1630,
    "venues": 13,
    "cities": 5,
    "fastfilling": 2,
    "housefull": 0,
    "occupancy": 16.81
  },
  "Send Help [MX4D 3D | English]": {
    "shows": 1,
    "gross": 16640.0,
    "sold": 32,
    "totalSeats": 80,
    "venues": 1,
    "cities": 1,
    "fastfilling": 0,
    "housefull": 0,
    "occupancy": 40.0
  },
  "Jai Kanhaiyalall Ki [2D | Gujarati]": {
    "shows": 2,
    "gross": 6140.0,
    "sold": 29,
    "totalSeats": 245,
    "venues": 2,
    "cities": 1,
    "fastfilling": 0,
    "housefull": 0,
    "occupancy": 11.84
  },
  "Zootopia 2 [MX4D 3D | English]": {
    "shows": 2,
    "gross": 32310.0,
    "sold": 60,
    "totalSeats": 156,
    "venues": 1,
    "cities": 1,
    "fastfilling": 0,
    "housefull": 0,
    "occupancy": 38.46
  },
  "Happy Patel: Khatarnak Jasoos [2D | Hindi]": {
    "shows": 12,
    "gross": 37855.0,
    "sold": 114,
    "totalSeats": 1421,
    "venues": 12,
    "cities": 3,
    "fastfilling": 0,
    "housefull": 0,
    "occupancy": 8.02
  },
  "Border 2 [4DX | Hindi]": {
    "shows": 9,
    "gross": 59790.0,
    "sold": 114,
    "totalSeats": 964,
    "venues": 9,
    "cities": 5,
    "fastfilling": 0,
    "housefull": 0,
    "occupancy": 11.83
  },
  "Tanvi: The Great [2D | Hindi]": {
    "shows": 1,
    "gross": 0.0,
    "sold": 0,
    "totalSeats": 46,
    "venues": 1,
    "cities": 1,
    "fastfilling": 0,
    "housefull": 0,
    "occupancy": 0.0
  },
  "The Raja Saab [2D | Hindi]": {
    "shows": 1,
    "gross": 1440.0,
    "sold": 9,
    "totalSeats": 105,
    "venues": 1,
    "cities": 1,
    "fastfilling": 0,
    "housefull": 0,
    "occupancy": 8.57
  },
  "One Two Cha Cha Chaa [2D | Hindi]": {
    "shows": 1,
    "gross": 0.0,
    "sold": 0,
    "totalSeats": 46,
    "venues": 1,
    "cities": 1,
    "fastfilling": 0,
    "housefull": 0,
    "occupancy": 0.0
  },
  "Chaurangi [2D | Gujarati]": {
    "shows": 5,
    "gross": 8390.0,
    "sold": 45,
    "totalSeats": 941,
    "venues": 5,
    "cities": 3,
    "fastfilling": 0,
    "housefull": 0,
    "occupancy": 4.78
  },
  "Laalo - Krishna Sada Sahaayate [2D | Gujarati]": {
    "shows": 2,
    "gross": 12680.0,
    "sold": 57,
    "totalSeats": 562,
    "venues": 2,
    "cities": 1,
    "fastfilling": 0,
    "housefull": 0,
    "occupancy": 10.14
  },
  "Cult (2026) [2D | Kannada]": {
    "shows": 7,
    "gross": 48800.0,
    "sold": 306,
    "totalSeats": 3505,
    "venues": 4,
    "cities": 3,
    "fastfilling": 0,
    "housefull": 0,
    "occupancy": 8.73
  },
  "Landlord [2D | Kannada]": {
    "shows": 10,
    "gross": 36400.0,
    "sold": 226,
    "totalSeats": 4143,
    "venues": 6,
    "cities": 3,
    "fastfilling": 0,
    "housefull": 0,
    "occupancy": 5.45
  },
  "Amruthaanjan [2D | Kannada]": {
    "shows": 4,
    "gross": 3150.0,
    "sold": 21,
    "totalSeats": 1510,
    "venues": 2,
    "cities": 2,
    "fastfilling": 0,
    "housefull": 0,
    "occupancy": 1.39
  },
  "Kab Hohi Milan [2D | Chattisgarhi]": {
    "shows": 2,
    "gross": 0.0,
    "sold": 0,
    "totalSeats": 108,
    "venues": 1,
    "cities": 1,
    "fastfilling": 0,
    "housefull": 0,
    "occupancy": 0.0
  },
  "Seat Edge [2D | Kannada]": {
    "shows": 1,
    "gross": 6400.0,
    "sold": 32,
    "totalSeats": 166,
    "venues": 1,
    "cities": 1,
    "fastfilling": 0,
    "housefull": 0,
    "occupancy": 19.28
  },
  "Raktha Kashmira [2D | Kannada]": {
    "shows": 2,
    "gross": 0.0,
    "sold": 0,
    "totalSeats": 826,
    "venues": 1,
    "cities": 1,
    "fastfilling": 0,
    "housefull": 0,
    "occupancy": 0.0
  },
  "Siharan [2D | Hindi]": {
    "shows": 2,
    "gross": 0.0,
    "sold": 0,
    "totalSeats": 200,
    "venues": 1,
    "cities": 1,
    "fastfilling": 0,
    "housefull": 0,
    "occupancy": 0.0
  },
  "Avatar: Fire and Ash [3D | Hindi]": {
    "shows": 4,
    "gross": 20910.0,
    "sold": 52,
    "totalSeats": 530,
    "venues": 4,
    "cities": 2,
    "fastfilling": 0,
    "housefull": 0,
    "occupancy": 9.81
  },
  "The SpongeBob Movie: Search for SquarePants [3D | English]": {
    "shows": 2,
    "gross": 3575.0,
    "sold": 11,
    "totalSeats": 101,
    "venues": 2,
    "cities": 2,
    "fastfilling": 0,
    "housefull": 0,
    "occupancy": 10.89
  },
  "Ikkis [2D | Hindi]": {
    "shows": 2,
    "gross": 8175.0,
    "sold": 28,
    "totalSeats": 178,
    "venues": 2,
    "cities": 2,
    "fastfilling": 0,
    "housefull": 0,
    "occupancy": 15.73
  },
  "Border 2 [ICE | Hindi]": {
    "shows": 4,
    "gross": 33090.0,
    "sold": 62,
    "totalSeats": 629,
    "venues": 2,
    "cities": 2,
    "fastfilling": 0,
    "housefull": 0,
    "occupancy": 9.86
  },
  "Bhanupriya Bhooter Hotel [2D | Bengali]": {
    "shows": 1,
    "gross": 2800.0,
    "sold": 12,
    "totalSeats": 198,
    "venues": 1,
    "cities": 1,
    "fastfilling": 0,
    "housefull": 0,
    "occupancy": 6.06
  },
  "Send Help [3D SCREEN X | English]": {
    "shows": 1,
    "gross": 1550.0,
    "sold": 5,
    "totalSeats": 294,
    "venues": 1,
    "cities": 1,
    "fastfilling": 0,
    "housefull": 0,
    "occupancy": 1.7
  },
  "Dilwale Dulhania Le Jayenge [2D | Hindi]": {
    "shows": 1,
    "gross": 3260.0,
    "sold": 74,
    "totalSeats": 1107,
    "venues": 1,
    "cities": 1,
    "fastfilling": 0,
    "housefull": 0,
    "occupancy": 6.68
  },
  "Malumadi [2D | Gujarati]": {
    "shows": 1,
    "gross": 0.0,
    "sold": 0,
    "totalSeats": 196,
    "venues": 1,
    "cities": 1,
    "fastfilling": 0,
    "housefull": 0,
    "occupancy": 0.0
  },
  "Prema Kadali [2D | Telugu]": {
    "shows": 1,
    "gross": 15400.0,
    "sold": 154,
    "totalSeats": 372,
    "venues": 1,
    "cities": 1,
    "fastfilling": 0,
    "housefull": 0,
    "occupancy": 41.4
  },
  "Anveshan [2D | Hindi]": {
    "shows": 1,
    "gross": 0.0,
    "sold": 0,
    "totalSeats": 60,
    "venues": 1,
    "cities": 1,
    "fastfilling": 0,
    "housefull": 0,
    "occupancy": 0.0
  },
  "Zootopia 2 [3D | English]": {
    "shows": 4,
    "gross": 13760.0,
    "sold": 47,
    "totalSeats": 376,
    "venues": 4,
    "cities": 3,
    "fastfilling": 0,
    "housefull": 0,
    "occupancy": 12.5
  },
  "Rahu Ketu [2D | Hindi]": {
    "shows": 3,
    "gross": 7960.0,
    "sold": 24,
    "totalSeats": 499,
    "venues": 3,
    "cities": 2,
    "fastfilling": 0,
    "housefull": 0,
    "occupancy": 4.81
  },
  "Granny [2D | Tamil]": {
    "shows": 1,
    "gross": 2700.0,
    "sold": 18,
    "totalSeats": 194,
    "venues": 1,
    "cities": 1,
    "fastfilling": 0,
    "housefull": 0,
    "occupancy": 9.28
  },
  "Bharathi Teacher [2D | Kannada]": {
    "shows": 1,
    "gross": 1236.0,
    "sold": 11,
    "totalSeats": 190,
    "venues": 1,
    "cities": 1,
    "fastfilling": 0,
    "housefull": 0,
    "occupancy": 5.79
  },
  "Mavuta [2D | Kannada]": {
    "shows": 1,
    "gross": 2400.0,
    "sold": 12,
    "totalSeats": 219,
    "venues": 1,
    "cities": 1,
    "fastfilling": 0,
    "housefull": 0,
    "occupancy": 5.48
  },
  "Teertharoopa Tandeyavarige [2D | Kannada]": {
    "shows": 1,
    "gross": 2200.0,
    "sold": 11,
    "totalSeats": 194,
    "venues": 1,
    "cities": 1,
    "fastfilling": 0,
    "housefull": 0,
    "occupancy": 5.67
  },
  "Zootopia 2 [3D | Hindi]": {
    "shows": 1,
    "gross": 2620.0,
    "sold": 8,
    "totalSeats": 65,
    "venues": 1,
    "cities": 1,
    "fastfilling": 0,
    "housefull": 0,
    "occupancy": 12.31
  },
  "Greenland 2: Migration [2D | English]": {
    "shows": 1,
    "gross": 2750.0,
    "sold": 11,
    "totalSeats": 49,
    "venues": 1,
    "cities": 1,
    "fastfilling": 0,
    "housefull": 0,
    "occupancy": 22.45
  },
  "Primate [2D | English]": {
    "shows": 2,
    "gross": 0.0,
    "sold": 0,
    "totalSeats": 178,
    "venues": 2,
    "cities": 2,
    "fastfilling": 0,
    "housefull": 0,
    "occupancy": 0.0
  },
  "Ameena [2D | Hindi]": {
    "shows": 1,
    "gross": 900.0,
    "sold": 9,
    "totalSeats": 63,
    "venues": 1,
    "cities": 1,
    "fastfilling": 0,
    "housefull": 0,
    "occupancy": 14.29
  }
}