{
  "Mana Shankara Vara Prasad Garu [2D | Telugu]": {
    "shows": 207,
    "gross": 1749466.0,
    "sold": 10922,
    "totalSeats": 84312,
    "venues": 94,
    "cities": 16,
    "fastfilling": 9,
    "housefull": 0,
    "occupancy": 12.95
  },
  "Anaganaga Oka Raju [2D | Telugu]": {
    "shows": 138,
    "gross": 1008994.0,
    "sold": 6074,
    "totalSeats": 47389,
    "venues": 78,
    "cities": 14,
    "fastfilling": 4,
    "housefull": 0,
    "occupancy": 12.82
  },
  "Mardaani 3 [2D | Hindi]": {
    "shows": 463,
    "gross": 4865949.0,
    "sold": 16692,
    "totalSeats": 100365,
    "venues": 171,
    "cities": 32,
    "fastfilling": 25,
    "housefull": 1,
    "occupancy": 16.63
  },
  "Mayasabha - The Hall of Illusion [2D | Hindi]": {
    "shows": 80,
    "gross": 312783.0,
    "sold": 1327,
    "totalSeats": 14660,
    "venues": 65,
    "cities": 18,
    "fastfilling": 3,
    "housefull": 1,
    "occupancy": 9.05
  },
  "Om Shanti Shanti Shantihi [2D | Telugu]": {
    "shows": 112,
    "gross": 686205.0,
    "sold": 5535,
    "totalSeats": 33791,
    "venues": 67,
    "cities": 10,
    "fastfilling": 5,
    "housefull": 0,
    "occupancy": 16.38
  },
  "Dhurandhar [2D | Hindi]": {
    "shows": 67,
    "gross": 408477.0,
    "sold": 1421,
    "totalSeats": 10703,
    "venues": 58,
    "cities": 14,
    "fastfilling": 2,
    "housefull": 0,
    "occupancy": 13.28
  },
  "Border 2 [2D | Hindi]": {
    "shows": 1094,
    "gross": 9238316.0,
    "sold": 30843,
    "totalSeats": 254331,
    "venues": 252,
    "cities": 64,
    "fastfilling": 30,
    "housefull": 4,
    "occupancy": 12.13
  },
  "Gandhi Talks [2D | Silent]": {
    "shows": 68,
    "gross": 227785.0,
    "sold": 819,
    "totalSeats": 12587,
    "venues": 52,
    "cities": 16,
    "fastfilling": 1,
    "housefull": 0,
    "occupancy": 6.51
  },
  "Nari Nari Naduma Murari [2D | Telugu]": {
    "shows": 132,
    "gross": 635956.0,
    "sold": 3790,
    "totalSeats": 42098,
    "venues": 73,
    "cities": 12,
    "fastfilling": 5,
    "housefull": 0,
    "occupancy": 9.0
  },
  "Demon Slayer: Kimetsu no Yaiba Infinity Castle [2D | Japanese]": {
    "shows": 1,
    "gross": 1800.0,
    "sold": 12,
    "totalSeats": 54,
    "venues": 1,
    "cities": 1,
    "fastfilling": 0,
    "housefull": 0,
    "occupancy": 22.22
  },
  "Marty Supreme [2D | English]": {
    "shows": 54,
    "gross": 375599.0,
    "sold": 1155,
    "totalSeats": 8329,
    "venues": 42,
    "cities": 10,
    "fastfilling": 1,
    "housefull": 0,
    "occupancy": 13.87
  },
  "Zootopia 2 [2D | English]": {
    "shows": 4,
    "gross": 15880.0,
    "sold": 74,
    "totalSeats": 332,
    "venues": 3,
    "cities": 2,
    "fastfilling": 0,
    "housefull": 0,
    "occupancy": 22.29
  },
  "One/4 [2D | Telugu]": {
    "shows": 7,
    "gross": 21448.0,
    "sold": 179,
    "totalSeats": 1353,
    "venues": 7,
    "cities": 3,
    "fastfilling": 1,
    "housefull": 0,
    "occupancy": 13.23
  },
  "Jagannath [2D | Telugu]": {
    "shows": 10,
    "gross": 20087.0,
    "sold": 119,
    "totalSeats": 2000,
    "venues": 10,
    "cities": 5,
    "fastfilling": 0,
    "housefull": 0,
    "occupancy": 5.95
  },
  "Send Help [3D | English]": {
    "shows": 72,
    "gross": 290613.0,
    "sold": 796,
    "totalSeats": 11375,
    "venues": 49,
    "cities": 12,
    "fastfilling": 2,
    "housefull": 0,
    "occupancy": 7.0
  },
  "The Raja Saab [2D | Telugu]": {
    "shows": 28,
    "gross": 204299.0,
    "sold": 1529,
    "totalSeats": 10380,
    "venues": 18,
    "cities": 5,
    "fastfilling": 0,
    "housefull": 0,
    "occupancy": 14.73
  },
  "Border 2 [4DX | Hindi]": {
    "shows": 22,
    "gross": 268220.0,
    "sold": 488,
    "totalSeats": 2336,
    "venues": 13,
    "cities": 7,
    "fastfilling": 0,
    "housefull": 0,
    "occupancy": 20.89
  },
  "The Housemaid [2D | English]": {
    "shows": 13,
    "gross": 67490.0,
    "sold": 152,
    "totalSeats": 1405,
    "venues": 12,
    "cities": 5,
    "fastfilling": 1,
    "housefull": 0,
    "occupancy": 10.82
  },
  "Zamana [2D | Telugu]": {
    "shows": 10,
    "gross": 100125.0,
    "sold": 837,
    "totalSeats": 4547,
    "venues": 7,
    "cities": 3,
    "fastfilling": 1,
    "housefull": 0,
    "occupancy": 18.41
  },
  "Trimukha [2D | Telugu]": {
    "shows": 11,
    "gross": 19432.0,
    "sold": 133,
    "totalSeats": 4502,
    "venues": 7,
    "cities": 6,
    "fastfilling": 0,
    "housefull": 0,
    "occupancy": 2.95
  },
  "Prakambanam [2D | Malayalam]": {
    "shows": 54,
    "gross": 484080.0,
    "sold": 2631,
    "totalSeats": 10909,
    "venues": 29,
    "cities": 12,
    "fastfilling": 11,
    "housefull": 1,
    "occupancy": 24.12
  },
  "Shelter [2D | English]": {
    "shows": 48,
    "gross": 214849.0,
    "sold": 546,
    "totalSeats": 6546,
    "venues": 31,
    "cities": 9,
    "fastfilling": 0,
    "housefull": 0,
    "occupancy": 8.34
  },
  "Bhartha Mahasayulaku Wignyapthi [2D | Telugu]": {
    "shows": 20,
    "gross": 86655.0,
    "sold": 556,
    "totalSeats": 4586,
    "venues": 12,
    "cities": 5,
    "fastfilling": 0,
    "housefull": 0,
    "occupancy": 12.12
  },
  "Send Help [2D | English]": {
    "shows": 26,
    "gross": 39620.0,
    "sold": 183,
    "totalSeats": 3986,
    "venues": 19,
    "cities": 6,
    "fastfilling": 0,
    "housefull": 0,
    "occupancy": 4.59
  },
  "Tere Ishk Mein [2D | Hindi]": {
    "shows": 3,
    "gross": 350.0,
    "sold": 5,
    "totalSeats": 660,
    "venues": 1,
    "cities": 1,
    "fastfilling": 0,
    "housefull": 0,
    "occupancy": 0.76
  },
  "Chatha Pacha: The Ring of Rowdies [2D | Malayalam]": {
    "shows": 101,
    "gross": 359479.99,
    "sold": 1869,
    "totalSeats": 25441,
    "venues": 41,
    "cities": 14,
    "fastfilling": 0,
    "housefull": 0,
    "occupancy": 7.35
  },
  "Valathu Vasathe Kallan [2D | Malayalam]": {
    "shows": 166,
    "gross": 1477152.23,
    "sold": 7282,
    "totalSeats": 48759,
    "venues": 57,
    "cities": 21,
    "fastfilling": 9,
    "housefull": 0,
    "occupancy": 14.93
  },
  "Lockdown [2D | Tamil]": {
    "shows": 14,
    "gross": 16660.0,
    "sold": 120,
    "totalSeats": 3560,
    "venues": 6,
    "cities": 6,
    "fastfilling": 0,
    "housefull": 0,
    "occupancy": 3.37
  },
  "Hot Spot 2 Much [2D | Tamil]": {
    "shows": 17,
    "gross": 24360.0,
    "sold": 163,
    "totalSeats": 6025,
    "venues": 7,
    "cities": 4,
    "fastfilling": 0,
    "housefull": 0,
    "occupancy": 2.71
  },
  "Krantijyoti Vidyalay Marathi Madhyam [2D | Marathi]": {
    "shows": 89,
    "gross": 526355.0,
    "sold": 2325,
    "totalSeats": 17602,
    "venues": 65,
    "cities": 7,
    "fastfilling": 3,
    "housefull": 0,
    "occupancy": 13.21
  },
  "Avatar: Fire and Ash [3D | English]": {
    "shows": 9,
    "gross": 54990.0,
    "sold": 134,
    "totalSeats": 1546,
    "venues": 9,
    "cities": 7,
    "fastfilling": 1,
    "housefull": 0,
    "occupancy": 8.67
  },
  "Baby Girl [2D | Malayalam]": {
    "shows": 52,
    "gross": 114044.0,
    "sold": 460,
    "totalSeats": 9242,
    "venues": 24,
    "cities": 12,
    "fastfilling": 0,
    "housefull": 0,
    "occupancy": 4.98
  },
  "Sarvam Maya [2D | Malayalam]": {
    "shows": 9,
    "gross": 38533.0,
    "sold": 200,
    "totalSeats": 1551,
    "venues": 5,
    "cities": 2,
    "fastfilling": 0,
    "housefull": 0,
    "occupancy": 12.89
  },
  "Border 2 [IMAX 2D | Hindi]": {
    "shows": 46,
    "gross": 765874.0,
    "sold": 1355,
    "totalSeats": 14061,
    "venues": 16,
    "cities": 7,
    "fastfilling": 0,
    "housefull": 0,
    "occupancy": 9.64
  },
  "Thalaivar Thambi Thalaimaiyil [2D | Tamil]": {
    "shows": 19,
    "gross": 45240.0,
    "sold": 307,
    "totalSeats": 5620,
    "venues": 8,
    "cities": 5,
    "fastfilling": 0,
    "housefull": 0,
    "occupancy": 5.46
  },
  "Magic Mushrooms [2D | Malayalam]": {
    "shows": 5,
    "gross": 4600.0,
    "sold": 28,
    "totalSeats": 748,
    "venues": 5,
    "cities": 4,
    "fastfilling": 0,
    "housefull": 0,
    "occupancy": 3.74
  },
  "Chatha Pacha: The Ring of Rowdies [2D | Tamil]": {
    "shows": 1,
    "gross": 2700.0,
    "sold": 18,
    "totalSeats": 194,
    "venues": 1,
    "cities": 1,
    "fastfilling": 0,
    "housefull": 0,
    "occupancy": 9.28
  },
  "Parasakthi [2D | Tamil]": {
    "shows": 5,
    "gross": 10210.0,
    "sold": 62,
    "totalSeats": 950,
    "venues": 2,
    "cities": 2,
    "fastfilling": 0,
    "housefull": 0,
    "occupancy": 6.53
  },
  "Karuppu Pulsar [2D | Tamil]": {
    "shows": 15,
    "gross": 51560.0,
    "sold": 374,
    "totalSeats": 4354,
    "venues": 7,
    "cities": 5,
    "fastfilling": 0,
    "housefull": 0,
    "occupancy": 8.59
  },
  "Sirai [2D | Tamil]": {
    "shows": 4,
    "gross": 10900.0,
    "sold": 91,
    "totalSeats": 1006,
    "venues": 2,
    "cities": 2,
    "fastfilling": 0,
    "housefull": 0,
    "occupancy": 9.05
  },
  "Devagudi [2D | Telugu]": {
    "shows": 24,
    "gross": 272651.0,
    "sold": 2294,
    "totalSeats": 6393,
    "venues": 17,
    "cities": 10,
    "fastfilling": 6,
    "housefull": 0,
    "occupancy": 35.88
  },
  "Dhrutarashtrudu [2D | Telugu]": {
    "shows": 9,
    "gross": 11985.0,
    "sold": 116,
    "totalSeats": 1766,
    "venues": 6,
    "cities": 3,
    "fastfilling": 0,
    "housefull": 0,
    "occupancy": 6.57
  },
  "Paree: An Unsolved Mystery [2D | Odia]": {
    "shows": 2,
    "gross": 0.0,
    "sold": 0,
    "totalSeats": 136,
    "venues": 1,
    "cities": 1,
    "fastfilling": 0,
    "housefull": 0,
    "occupancy": 0.0
  },
  "Vijaynagar'er Hirey (Kakababu) [2D | Bengali]": {
    "shows": 7,
    "gross": 12600.0,
    "sold": 49,
    "totalSeats": 1072,
    "venues": 6,
    "cities": 5,
    "fastfilling": 0,
    "housefull": 0,
    "occupancy": 4.57
  },
  "Hok Kolorob [2D | Bengali]": {
    "shows": 3,
    "gross": 2400.0,
    "sold": 12,
    "totalSeats": 480,
    "venues": 2,
    "cities": 2,
    "fastfilling": 0,
    "housefull": 0,
    "occupancy": 2.5
  },
  "Kattemar [2D | Tulu]": {
    "shows": 8,
    "gross": 9200.0,
    "sold": 63,
    "totalSeats": 1252,
    "venues": 2,
    "cities": 1,
    "fastfilling": 0,
    "housefull": 0,
    "occupancy": 5.03
  },
  "Landlord [2D | Kannada]": {
    "shows": 15,
    "gross": 51380.0,
    "sold": 318,
    "totalSeats": 6177,
    "venues": 7,
    "cities": 4,
    "fastfilling": 0,
    "housefull": 0,
    "occupancy": 5.15
  },
  "Mankatha [2D | Tamil]": {
    "shows": 10,
    "gross": 5440.0,
    "sold": 49,
    "totalSeats": 3090,
    "venues": 4,
    "cities": 4,
    "fastfilling": 0,
    "housefull": 0,
    "occupancy": 1.59
  },
  "Aga Aga Sunbai! Kay Mhantay Sasubai? [2D | Marathi]": {
    "shows": 75,
    "gross": 612418.0,
    "sold": 2780,
    "totalSeats": 14273,
    "venues": 55,
    "cities": 9,
    "fastfilling": 6,
    "housefull": 0,
    "occupancy": 19.48
  },
  "Mercy [3D | English]": {
    "shows": 9,
    "gross": 21550.0,
    "sold": 73,
    "totalSeats": 1020,
    "venues": 9,
    "cities": 6,
    "fastfilling": 0,
    "housefull": 0,
    "occupancy": 7.16
  },
  "Chaurangi [2D | Gujarati]": {
    "shows": 9,
    "gross": 12330.0,
    "sold": 58,
    "totalSeats": 1409,
    "venues": 7,
    "cities": 3,
    "fastfilling": 0,
    "housefull": 0,
    "occupancy": 4.12
  },
  "Happy Patel: Khatarnak Jasoos [2D | Hindi]": {
    "shows": 14,
    "gross": 61895.0,
    "sold": 150,
    "totalSeats": 1503,
    "venues": 14,
    "cities": 4,
    "fastfilling": 0,
    "housefull": 0,
    "occupancy": 9.98
  },
  "Send Help [MX4D 3D | English]": {
    "shows": 2,
    "gross": 36960.0,
    "sold": 63,
    "totalSeats": 156,
    "venues": 1,
    "cities": 1,
    "fastfilling": 0,
    "housefull": 0,
    "occupancy": 40.38
  },
  "Human Cocaine [2D | Hindi]": {
    "shows": 15,
    "gross": 81635.0,
    "sold": 293,
    "totalSeats": 1857,
    "venues": 15,
    "cities": 6,
    "fastfilling": 2,
    "housefull": 0,
    "occupancy": 15.78
  },
  "Send Help [4DX 3D | English]": {
    "shows": 17,
    "gross": 100215.0,
    "sold": 207,
    "totalSeats": 1860,
    "venues": 13,
    "cities": 7,
    "fastfilling": 0,
    "housefull": 0,
    "occupancy": 11.13
  },
  "One Two Cha Cha Chaa [2D | Hindi]": {
    "shows": 1,
    "gross": 2240.0,
    "sold": 14,
    "totalSeats": 46,
    "venues": 1,
    "cities": 1,
    "fastfilling": 0,
    "housefull": 0,
    "occupancy": 30.43
  },
  "Jai Kanhaiyalall Ki [2D | Gujarati]": {
    "shows": 3,
    "gross": 7530.0,
    "sold": 28,
    "totalSeats": 290,
    "venues": 3,
    "cities": 1,
    "fastfilling": 0,
    "housefull": 0,
    "occupancy": 9.66
  },
  "Faatho Aah Bhagwaan 2 [2D | Sindhi]": {
    "shows": 1,
    "gross": 500.0,
    "sold": 2,
    "totalSeats": 138,
    "venues": 1,
    "cities": 1,
    "fastfilling": 0,
    "housefull": 0,
    "occupancy": 1.45
  },
  "Paatki [2D | Gujarati]": {
    "shows": 2,
    "gross": 4940.0,
    "sold": 17,
    "totalSeats": 299,
    "venues": 2,
    "cities": 1,
    "fastfilling": 0,
    "housefull": 0,
    "occupancy": 5.69
  },
  "Shambhala [2D | Hindi]": {
    "shows": 1,
    "gross": 120.0,
    "sold": 1,
    "totalSeats": 354,
    "venues": 1,
    "cities": 1,
    "fastfilling": 0,
    "housefull": 0,
    "occupancy": 0.28
  },
  "Cult (2026) [2D | Kannada]": {
    "shows": 11,
    "gross": 71850.0,
    "sold": 450,
    "totalSeats": 5358,
    "venues": 4,
    "cities": 3,
    "fastfilling": 0,
    "housefull": 0,
    "occupancy": 8.4
  },
  "Amruthaanjan [2D | Kannada]": {
    "shows": 6,
    "gross": 3150.0,
    "sold": 21,
    "totalSeats": 2265,
    "venues": 2,
    "cities": 2,
    "fastfilling": 0,
    "housefull": 0,
    "occupancy": 0.93
  },
  "Kab Hohi Milan [2D | Chattisgarhi]": {
    "shows": 3,
    "gross": 0.0,
    "sold": 0,
    "totalSeats": 162,
    "venues": 1,
    "cities": 1,
    "fastfilling": 0,
    "housefull": 0,
    "occupancy": 0.0
  },
  "Valavaara [2D | Kannada]": {
    "shows": 1,
    "gross": 6450.0,
    "sold": 39,
    "totalSeats": 166,
    "venues": 1,
    "cities": 1,
    "fastfilling": 0,
    "housefull": 0,
    "occupancy": 23.49
  },
  "Vikalpa [2D | Kannada]": {
    "shows": 1,
    "gross": 14850.0,
    "sold": 84,
    "totalSeats": 219,
    "venues": 1,
    "cities": 1,
    "fastfilling": 0,
    "housefull": 0,
    "occupancy": 38.36
  },
  "Raktha Kashmira [2D | Kannada]": {
    "shows": 3,
    "gross": 0.0,
    "sold": 0,
    "totalSeats": 1239,
    "venues": 1,
    "cities": 1,
    "fastfilling": 0,
    "housefull": 0,
    "occupancy": 0.0
  },
  "Christina [2D | Malayalam]": {
    "shows": 3,
    "gross": 8120.0,
    "sold": 47,
    "totalSeats": 428,
    "venues": 3,
    "cities": 2,
    "fastfilling": 0,
    "housefull": 0,
    "occupancy": 10.98
  },
  "Prema Kadali [2D | Telugu]": {
    "shows": 2,
    "gross": 16100.0,
    "sold": 161,
    "totalSeats": 744,
    "venues": 1,
    "cities": 1,
    "fastfilling": 0,
    "housefull": 0,
    "occupancy": 21.64
  },
  "Anveshan [2D | Hindi]": {
    "shows": 2,
    "gross": 0.0,
    "sold": 0,
    "totalSeats": 120,
    "venues": 1,
    "cities": 1,
    "fastfilling": 0,
    "housefull": 0,
    "occupancy": 0.0
  },
  "Siharan [2D | Hindi]": {
    "shows": 3,
    "gross": 0.0,
    "sold": 0,
    "totalSeats": 300,
    "venues": 1,
    "cities": 1,
    "fastfilling": 0,
    "housefull": 0,
    "occupancy": 0.0
  },
  "Seat Edge [2D | Kannada]": {
    "shows": 2,
    "gross": 19830.0,
    "sold": 99,
    "totalSeats": 367,
    "venues": 2,
    "cities": 2,
    "fastfilling": 0,
    "housefull": 0,
    "occupancy": 26.98
  },
  "Chowkidar [2D | Kannada]": {
    "shows": 5,
    "gross": 3450.0,
    "sold": 18,
    "totalSeats": 2533,
    "venues": 3,
    "cities": 3,
    "fastfilling": 0,
    "housefull": 0,
    "occupancy": 0.71
  },
  "Zootopia 2 [3D | English]": {
    "shows": 7,
    "gross": 33600.0,
    "sold": 98,
    "totalSeats": 542,
    "venues": 6,
    "cities": 4,
    "fastfilling": 1,
    "housefull": 0,
    "occupancy": 18.08
  },
  "Border 2 [ICE | Hindi]": {
    "shows": 6,
    "gross": 62730.0,
    "sold": 114,
    "totalSeats": 960,
    "venues": 2,
    "cities": 2,
    "fastfilling": 0,
    "housefull": 0,
    "occupancy": 11.88
  },
  "Zootopia 2 [MX4D 3D | English]": {
    "shows": 2,
    "gross": 29750.0,
    "sold": 56,
    "totalSeats": 156,
    "venues": 1,
    "cities": 1,
    "fastfilling": 0,
    "housefull": 0,
    "occupancy": 35.9
  },
  "Mellisai [2D | Tamil]": {
    "shows": 1,
    "gross": 2700.0,
    "sold": 18,
    "totalSeats": 194,
    "venues": 1,
    "cities": 1,
    "fastfilling": 0,
    "housefull": 0,
    "occupancy": 9.28
  },
  "Jockey [2D | Tamil]": {
    "shows": 1,
    "gross": 0.0,
    "sold": 0,
    "totalSeats": 163,
    "venues": 1,
    "cities": 1,
    "fastfilling": 0,
    "housefull": 0,
    "occupancy": 0.0
  },
  "Tanvi: The Great [2D | Hindi]": {
    "shows": 1,
    "gross": 2560.0,
    "sold": 16,
    "totalSeats": 46,
    "venues": 1,
    "cities": 1,
    "fastfilling": 0,
    "housefull": 0,
    "occupancy": 34.78
  },
  "The Raja Saab [2D | Hindi]": {
    "shows": 1,
    "gross": 1440.0,
    "sold": 9,
    "totalSeats": 105,
    "venues": 1,
    "cities": 1,
    "fastfilling": 0,
    "housefull": 0,
    "occupancy": 8.57
  },
  "Laalo - Krishna Sada Sahaayate [2D | Gujarati]": {
    "shows": 2,
    "gross": 14000.0,
    "sold": 63,
    "totalSeats": 562,
    "venues": 2,
    "cities": 1,
    "fastfilling": 0,
    "housefull": 0,
    "occupancy": 11.21
  },
  "Tomar Jonyo  [2D | Bengali]": {
    "shows": 1,
    "gross": 0.0,
    "sold": 0,
    "totalSeats": 60,
    "venues": 1,
    "cities": 1,
    "fastfilling": 0,
    "housefull": 0,
    "occupancy": 0.0
  },
  "Avatar: Fire and Ash [3D | Hindi]": {
    "shows": 4,
    "gross": 25990.0,
    "sold": 63,
    "totalSeats": 530,
    "venues": 4,
    "cities": 2,
    "fastfilling": 0,
    "housefull": 0,
    "occupancy": 11.89
  },
  "The SpongeBob Movie: Search for SquarePants [3D | English]": {
    "shows": 2,
    "gross": 4555.0,
    "sold": 13,
    "totalSeats": 107,
    "venues": 2,
    "cities": 2,
    "fastfilling": 0,
    "housefull": 0,
    "occupancy": 12.15
  },
  "Avatar: Fire and Ash [4DX 3D | English]": {
    "shows": 3,
    "gross": 27154.0,
    "sold": 67,
    "totalSeats": 320,
    "venues": 3,
    "cities": 3,
    "fastfilling": 0,
    "housefull": 0,
    "occupancy": 20.94
  },
  "Chatha Pacha: The Ring of Rowdies [2D | Telugu]": {
    "shows": 5,
    "gross": 2600.0,
    "sold": 13,
    "totalSeats": 1113,
    "venues": 5,
    "cities": 1,
    "fastfilling": 0,
    "housefull": 0,
    "occupancy": 1.17
  },
  "Thiraivi [2D | Tamil]": {
    "shows": 1,
    "gross": 0.0,
    "sold": 0,
    "totalSeats": 170,
    "venues": 1,
    "cities": 1,
    "fastfilling": 0,
    "housefull": 0,
    "occupancy": 0.0
  },
  "Ikkis [2D | Hindi]": {
    "shows": 2,
    "gross": 8175.0,
    "sold": 28,
    "totalSeats": 178,
    "venues": 2,
    "cities": 2,
    "fastfilling": 0,
    "housefull": 0,
    "occupancy": 15.73
  },
  "Bhanupriya Bhooter Hotel [2D | Bengali]": {
    "shows": 1,
    "gross": 2800.0,
    "sold": 12,
    "totalSeats": 198,
    "venues": 1,
    "cities": 1,
    "fastfilling": 0,
    "housefull": 0,
    "occupancy": 6.06
  },
  "Send Help [3D SCREEN X | English]": {
    "shows": 1,
    "gross": 1550.0,
    "sold": 5,
    "totalSeats": 294,
    "venues": 1,
    "cities": 1,
    "fastfilling": 0,
    "housefull": 0,
    "occupancy": 1.7
  },
  "Dilwale Dulhania Le Jayenge [2D | Hindi]": {
    "shows": 1,
    "gross": 3260.0,
    "sold": 74,
    "totalSeats": 1107,
    "venues": 1,
    "cities": 1,
    "fastfilling": 0,
    "housefull": 0,
    "occupancy": 6.68
  },
  "Malumadi [2D | Gujarati]": {
    "shows": 1,
    "gross": 0.0,
    "sold": 0,
    "totalSeats": 196,
    "venues": 1,
    "cities": 1,
    "fastfilling": 0,
    "housefull": 0,
    "occupancy": 0.0
  },
  "Rahu Ketu [2D | Hindi]": {
    "shows": 3,
    "gross": 7960.0,
    "sold": 24,
    "totalSeats": 499,
    "venues": 3,
    "cities": 2,
    "fastfilling": 0,
    "housefull": 0,
    "occupancy": 4.81
  },
  "Granny [2D | Tamil]": {
    "shows": 1,
    "gross": 2700.0,
    "sold": 18,
    "totalSeats": 194,
    "venues": 1,
    "cities": 1,
    "fastfilling": 0,
    "housefull": 0,
    "occupancy": 9.28
  },
  "Bharathi Teacher [2D | Kannada]": {
    "shows": 1,
    "gross": 1236.0,
    "sold": 11,
    "totalSeats": 190,
    "venues": 1,
    "cities": 1,
    "fastfilling": 0,
    "housefull": 0,
    "occupancy": 5.79
  },
  "Mavuta [2D | Kannada]": {
    "shows": 1,
    "gross": 2400.0,
    "sold": 12,
    "totalSeats": 219,
    "venues": 1,
    "cities": 1,
    "fastfilling": 0,
    "housefull": 0,
    "occupancy": 5.48
  },
  "Teertharoopa Tandeyavarige [2D | Kannada]": {
    "shows": 1,
    "gross": 2200.0,
    "sold": 11,
    "totalSeats": 194,
    "venues": 1,
    "cities": 1,
    "fastfilling": 0,
    "housefull": 0,
    "occupancy": 5.67
  },
  "Zootopia 2 [3D | Hindi]": {
    "shows": 1,
    "gross": 2620.0,
    "sold": 8,
    "totalSeats": 65,
    "venues": 1,
    "cities": 1,
    "fastfilling": 0,
    "housefull": 0,
    "occupancy": 12.31
  },
  "Greenland 2: Migration [2D | English]": {
    "shows": 1,
    "gross": 2750.0,
    "sold": 11,
    "totalSeats": 49,
    "venues": 1,
    "cities": 1,
    "fastfilling": 0,
    "housefull": 0,
    "occupancy": 22.45
  },
  "Primate [2D | English]": {
    "shows": 2,
    "gross": 0.0,
    "sold": 0,
    "totalSeats": 178,
    "venues": 2,
    "cities": 2,
    "fastfilling": 0,
    "housefull": 0,
    "occupancy": 0.0
  },
  "Ameena [2D | Hindi]": {
    "shows": 1,
    "gross": 900.0,
    "sold": 9,
    "totalSeats": 63,
    "venues": 1,
    "cities": 1,
    "fastfilling": 0,
    "housefull": 0,
    "occupancy": 14.29
  }
}