{
  "Valathu Vasathe Kallan [2D | Malayalam]": {
    "shows": 249,
    "gross": 2204176.9,
    "sold": 10822,
    "totalSeats": 74724,
    "venues": 75,
    "cities": 24,
    "fastfilling": 22,
    "housefull": 0,
    "occupancy": 14.48
  },
  "Chatha Pacha: The Ring of Rowdies [2D | Malayalam]": {
    "shows": 158,
    "gross": 572821.0,
    "sold": 2842,
    "totalSeats": 29658,
    "venues": 58,
    "cities": 19,
    "fastfilling": 2,
    "housefull": 0,
    "occupancy": 9.58
  },
  "Border 2 [2D | Hindi]": {
    "shows": 1371,
    "gross": 9435895.0,
    "sold": 36668,
    "totalSeats": 284718,
    "venues": 247,
    "cities": 83,
    "fastfilling": 44,
    "housefull": 4,
    "occupancy": 12.88
  },
  "Mardaani 3 [2D | Hindi]": {
    "shows": 623,
    "gross": 4239007.0,
    "sold": 15833,
    "totalSeats": 123229,
    "venues": 159,
    "cities": 46,
    "fastfilling": 24,
    "housefull": 0,
    "occupancy": 12.85
  },
  "Send Help [3D | English]": {
    "shows": 84,
    "gross": 205552.0,
    "sold": 701,
    "totalSeats": 15797,
    "venues": 46,
    "cities": 10,
    "fastfilling": 0,
    "housefull": 0,
    "occupancy": 4.44
  },
  "Lockdown [2D | Tamil]": {
    "shows": 18,
    "gross": 62036.4,
    "sold": 438,
    "totalSeats": 6042,
    "venues": 9,
    "cities": 6,
    "fastfilling": 0,
    "housefull": 1,
    "occupancy": 7.25
  },
  "Om Shanti Shanti Shantihi [2D | Telugu]": {
    "shows": 54,
    "gross": 175316.0,
    "sold": 1337,
    "totalSeats": 18245,
    "venues": 30,
    "cities": 9,
    "fastfilling": 4,
    "housefull": 0,
    "occupancy": 7.33
  },
  "Anaganaga Oka Raju [2D | Telugu]": {
    "shows": 64,
    "gross": 358534.0,
    "sold": 2008,
    "totalSeats": 16281,
    "venues": 31,
    "cities": 10,
    "fastfilling": 4,
    "housefull": 0,
    "occupancy": 12.33
  },
  "Karuppu Pulsar [2D | Tamil]": {
    "shows": 18,
    "gross": 55666.3,
    "sold": 449,
    "totalSeats": 8462,
    "venues": 7,
    "cities": 5,
    "fastfilling": 0,
    "housefull": 1,
    "occupancy": 5.31
  },
  "Thalaivar Thambi Thalaimaiyil [2D | Tamil]": {
    "shows": 42,
    "gross": 177964.45,
    "sold": 1438,
    "totalSeats": 15334,
    "venues": 18,
    "cities": 7,
    "fastfilling": 3,
    "housefull": 0,
    "occupancy": 9.38
  },
  "Ninaithathai Mudippavan [2D | Tamil]": {
    "shows": 2,
    "gross": 0.0,
    "sold": 0,
    "totalSeats": 790,
    "venues": 1,
    "cities": 1,
    "fastfilling": 0,
    "housefull": 0,
    "occupancy": 0.0
  },
  "Mana Shankara Vara Prasad Garu [2D | Telugu]": {
    "shows": 115,
    "gross": 1083160.0,
    "sold": 6932,
    "totalSeats": 42758,
    "venues": 54,
    "cities": 13,
    "fastfilling": 11,
    "housefull": 0,
    "occupancy": 16.21
  },
  "Bhartha Mahasayulaku Wignyapthi [2D | Telugu]": {
    "shows": 34,
    "gross": 142914.0,
    "sold": 1281,
    "totalSeats": 10487,
    "venues": 10,
    "cities": 8,
    "fastfilling": 0,
    "housefull": 1,
    "occupancy": 12.22
  },
  "Devagudi [2D | Telugu]": {
    "shows": 14,
    "gross": 27621.0,
    "sold": 252,
    "totalSeats": 5234,
    "venues": 4,
    "cities": 4,
    "fastfilling": 0,
    "housefull": 0,
    "occupancy": 4.81
  },
  "One/4 [2D | Telugu]": {
    "shows": 7,
    "gross": 10500.0,
    "sold": 169,
    "totalSeats": 3019,
    "venues": 3,
    "cities": 3,
    "fastfilling": 0,
    "housefull": 0,
    "occupancy": 5.6
  },
  "Prakambanam [2D | Malayalam]": {
    "shows": 121,
    "gross": 1067573.3,
    "sold": 5832,
    "totalSeats": 29744,
    "venues": 48,
    "cities": 13,
    "fastfilling": 21,
    "housefull": 0,
    "occupancy": 19.61
  },
  "Nari Nari Naduma Murari [2D | Telugu]": {
    "shows": 56,
    "gross": 354893.0,
    "sold": 2204,
    "totalSeats": 14346,
    "venues": 27,
    "cities": 11,
    "fastfilling": 5,
    "housefull": 0,
    "occupancy": 15.36
  },
  "Sarvam Maya [2D | Malayalam]": {
    "shows": 20,
    "gross": 53967.3,
    "sold": 296,
    "totalSeats": 3403,
    "venues": 10,
    "cities": 5,
    "fastfilling": 0,
    "housefull": 0,
    "occupancy": 8.7
  },
  "Gandhi Talks [2D | Silent]": {
    "shows": 76,
    "gross": 223319.5,
    "sold": 1151,
    "totalSeats": 13490,
    "venues": 43,
    "cities": 14,
    "fastfilling": 2,
    "housefull": 0,
    "occupancy": 8.53
  },
  "Hot Spot 2 Much [2D | Tamil]": {
    "shows": 7,
    "gross": 15581.4,
    "sold": 184,
    "totalSeats": 1958,
    "venues": 3,
    "cities": 2,
    "fastfilling": 0,
    "housefull": 0,
    "occupancy": 9.4
  },
  "Mellisai [2D | Tamil]": {
    "shows": 4,
    "gross": 8573.8,
    "sold": 70,
    "totalSeats": 847,
    "venues": 3,
    "cities": 1,
    "fastfilling": 0,
    "housefull": 0,
    "occupancy": 8.26
  },
  "Thiraivi [2D | Tamil]": {
    "shows": 3,
    "gross": 2482.3,
    "sold": 29,
    "totalSeats": 1021,
    "venues": 2,
    "cities": 2,
    "fastfilling": 0,
    "housefull": 0,
    "occupancy": 2.84
  },
  "Chaurangi [2D | Gujarati]": {
    "shows": 21,
    "gross": 17690.0,
    "sold": 85,
    "totalSeats": 3236,
    "venues": 16,
    "cities": 4,
    "fastfilling": 0,
    "housefull": 0,
    "occupancy": 2.63
  },
  "Paatki [2D | Gujarati]": {
    "shows": 40,
    "gross": 45480.0,
    "sold": 254,
    "totalSeats": 6502,
    "venues": 28,
    "cities": 5,
    "fastfilling": 0,
    "housefull": 0,
    "occupancy": 3.91
  },
  "Mersal [2D | Tamil]": {
    "shows": 4,
    "gross": 3900.0,
    "sold": 31,
    "totalSeats": 2095,
    "venues": 2,
    "cities": 2,
    "fastfilling": 0,
    "housefull": 0,
    "occupancy": 1.48
  },
  "Jockey [2D | Tamil]": {
    "shows": 2,
    "gross": 100.0,
    "sold": 1,
    "totalSeats": 878,
    "venues": 1,
    "cities": 1,
    "fastfilling": 0,
    "housefull": 0,
    "occupancy": 0.11
  },
  "The Raja Saab [2D | Telugu]": {
    "shows": 10,
    "gross": 45255.0,
    "sold": 330,
    "totalSeats": 4902,
    "venues": 3,
    "cities": 3,
    "fastfilling": 0,
    "housefull": 0,
    "occupancy": 6.73
  },
  "Trimukha [2D | Telugu]": {
    "shows": 9,
    "gross": 42032.0,
    "sold": 410,
    "totalSeats": 3754,
    "venues": 4,
    "cities": 3,
    "fastfilling": 0,
    "housefull": 0,
    "occupancy": 10.92
  },
  "Zamana [2D | Telugu]": {
    "shows": 7,
    "gross": 100725.0,
    "sold": 690,
    "totalSeats": 1658,
    "venues": 2,
    "cities": 2,
    "fastfilling": 3,
    "housefull": 0,
    "occupancy": 41.62
  },
  "Shelter [2D | English]": {
    "shows": 29,
    "gross": 145580.0,
    "sold": 456,
    "totalSeats": 4379,
    "venues": 13,
    "cities": 6,
    "fastfilling": 0,
    "housefull": 0,
    "occupancy": 10.41
  },
  "Marty Supreme [2D | English]": {
    "shows": 41,
    "gross": 448350.0,
    "sold": 1206,
    "totalSeats": 6382,
    "venues": 20,
    "cities": 8,
    "fastfilling": 6,
    "housefull": 0,
    "occupancy": 18.9
  },
  "Cult (2026) [2D | Kannada]": {
    "shows": 47,
    "gross": 608230.0,
    "sold": 2413,
    "totalSeats": 17111,
    "venues": 26,
    "cities": 2,
    "fastfilling": 4,
    "housefull": 0,
    "occupancy": 14.1
  },
  "Landlord [2D | Kannada]": {
    "shows": 132,
    "gross": 991330.0,
    "sold": 6157,
    "totalSeats": 65552,
    "venues": 51,
    "cities": 4,
    "fastfilling": 4,
    "housefull": 0,
    "occupancy": 9.39
  },
  "Raktha Kashmira [2D | Kannada]": {
    "shows": 59,
    "gross": 169690.0,
    "sold": 1090,
    "totalSeats": 20021,
    "venues": 32,
    "cities": 2,
    "fastfilling": 0,
    "housefull": 0,
    "occupancy": 5.44
  },
  "Vikalpa [2D | Kannada]": {
    "shows": 6,
    "gross": 60530.0,
    "sold": 267,
    "totalSeats": 898,
    "venues": 6,
    "cities": 2,
    "fastfilling": 2,
    "housefull": 0,
    "occupancy": 29.73
  },
  "Magic Mushrooms [2D | Malayalam]": {
    "shows": 14,
    "gross": 13500.0,
    "sold": 64,
    "totalSeats": 2623,
    "venues": 10,
    "cities": 4,
    "fastfilling": 0,
    "housefull": 0,
    "occupancy": 2.44
  },
  "Christina [2D | Malayalam]": {
    "shows": 13,
    "gross": 4110.0,
    "sold": 23,
    "totalSeats": 2216,
    "venues": 10,
    "cities": 3,
    "fastfilling": 0,
    "housefull": 0,
    "occupancy": 1.04
  },
  "Baby Girl [2D | Malayalam]": {
    "shows": 68,
    "gross": 114406.6,
    "sold": 566,
    "totalSeats": 11994,
    "venues": 30,
    "cities": 13,
    "fastfilling": 0,
    "housefull": 0,
    "occupancy": 4.72
  },
  "Dhurandhar [2D | Hindi]": {
    "shows": 54,
    "gross": 338964.0,
    "sold": 1155,
    "totalSeats": 8256,
    "venues": 44,
    "cities": 15,
    "fastfilling": 1,
    "housefull": 0,
    "occupancy": 13.99
  },
  "Mayasabha - The Hall of Illusion [2D | Hindi]": {
    "shows": 52,
    "gross": 126789.0,
    "sold": 669,
    "totalSeats": 9311,
    "venues": 42,
    "cities": 19,
    "fastfilling": 0,
    "housefull": 0,
    "occupancy": 7.19
  },
  "Aga Aga Sunbai! Kay Mhantay Sasubai? [2D | Marathi]": {
    "shows": 19,
    "gross": 110895.0,
    "sold": 865,
    "totalSeats": 4052,
    "venues": 13,
    "cities": 10,
    "fastfilling": 4,
    "housefull": 0,
    "occupancy": 21.35
  },
  "Send Help [4DX 3D | English]": {
    "shows": 18,
    "gross": 118850.0,
    "sold": 225,
    "totalSeats": 1758,
    "venues": 9,
    "cities": 5,
    "fastfilling": 0,
    "housefull": 0,
    "occupancy": 12.8
  },
  "Avatar: Fire and Ash [4DX 3D | English]": {
    "shows": 5,
    "gross": 41310.0,
    "sold": 85,
    "totalSeats": 452,
    "venues": 4,
    "cities": 2,
    "fastfilling": 0,
    "housefull": 0,
    "occupancy": 18.81
  },
  "Border 2 [IMAX 2D | Hindi]": {
    "shows": 26,
    "gross": 332290.0,
    "sold": 800,
    "totalSeats": 7539,
    "venues": 7,
    "cities": 2,
    "fastfilling": 0,
    "housefull": 0,
    "occupancy": 10.61
  },
  "Send Help [2D | English]": {
    "shows": 29,
    "gross": 53050.0,
    "sold": 229,
    "totalSeats": 5272,
    "venues": 18,
    "cities": 8,
    "fastfilling": 0,
    "housefull": 0,
    "occupancy": 4.34
  },
  "Border 2 [4DX | Hindi]": {
    "shows": 21,
    "gross": 226400.0,
    "sold": 448,
    "totalSeats": 2090,
    "venues": 9,
    "cities": 5,
    "fastfilling": 3,
    "housefull": 0,
    "occupancy": 21.44
  },
  "Vaama: Ladai Sanmanachi [2D | Marathi]": {
    "shows": 2,
    "gross": 0.0,
    "sold": 0,
    "totalSeats": 500,
    "venues": 1,
    "cities": 1,
    "fastfilling": 0,
    "housefull": 0,
    "occupancy": 0.0
  },
  "Send Help [MX4D 3D | English]": {
    "shows": 3,
    "gross": 9020.0,
    "sold": 22,
    "totalSeats": 279,
    "venues": 1,
    "cities": 1,
    "fastfilling": 0,
    "housefull": 0,
    "occupancy": 7.89
  },
  "Vijaynagar'er Hirey (Kakababu) [2D | Bengali]": {
    "shows": 19,
    "gross": 57420.0,
    "sold": 272,
    "totalSeats": 2574,
    "venues": 10,
    "cities": 6,
    "fastfilling": 1,
    "housefull": 0,
    "occupancy": 10.57
  },
  "Mankatha [2D | Tamil]": {
    "shows": 27,
    "gross": 46230.09,
    "sold": 352,
    "totalSeats": 9218,
    "venues": 19,
    "cities": 7,
    "fastfilling": 0,
    "housefull": 0,
    "occupancy": 3.82
  },
  "Avatar: Fire and Ash [3D | English]": {
    "shows": 11,
    "gross": 74975.0,
    "sold": 222,
    "totalSeats": 1322,
    "venues": 6,
    "cities": 1,
    "fastfilling": 0,
    "housefull": 0,
    "occupancy": 16.79
  },
  "Amruthaanjan [2D | Kannada]": {
    "shows": 37,
    "gross": 409580.0,
    "sold": 2452,
    "totalSeats": 13209,
    "venues": 25,
    "cities": 2,
    "fastfilling": 2,
    "housefull": 0,
    "occupancy": 18.56
  },
  "Chowkidar [2D | Kannada]": {
    "shows": 24,
    "gross": 70350.0,
    "sold": 484,
    "totalSeats": 8481,
    "venues": 17,
    "cities": 2,
    "fastfilling": 1,
    "housefull": 0,
    "occupancy": 5.71
  },
  "Human Cocaine [2D | Hindi]": {
    "shows": 24,
    "gross": 36275.0,
    "sold": 218,
    "totalSeats": 3979,
    "venues": 23,
    "cities": 12,
    "fastfilling": 0,
    "housefull": 0,
    "occupancy": 5.48
  },
  "Granny [2D | Tamil]": {
    "shows": 5,
    "gross": 11070.0,
    "sold": 86,
    "totalSeats": 1287,
    "venues": 4,
    "cities": 2,
    "fastfilling": 0,
    "housefull": 0,
    "occupancy": 6.68
  },
  "Sri Jagannatha Dasaru: Part 2 [2D | Kannada]": {
    "shows": 7,
    "gross": 34310.0,
    "sold": 133,
    "totalSeats": 1544,
    "venues": 7,
    "cities": 2,
    "fastfilling": 0,
    "housefull": 0,
    "occupancy": 8.61
  },
  "Teertharoopa Tandeyavarige [2D | Kannada]": {
    "shows": 4,
    "gross": 10820.0,
    "sold": 60,
    "totalSeats": 441,
    "venues": 3,
    "cities": 2,
    "fastfilling": 0,
    "housefull": 0,
    "occupancy": 13.61
  },
  "Mavuta [2D | Kannada]": {
    "shows": 9,
    "gross": 45260.0,
    "sold": 362,
    "totalSeats": 4644,
    "venues": 6,
    "cities": 2,
    "fastfilling": 0,
    "housefull": 0,
    "occupancy": 7.8
  },
  "Draupathi 2 [2D | Tamil]": {
    "shows": 4,
    "gross": 1350.0,
    "sold": 15,
    "totalSeats": 3528,
    "venues": 1,
    "cities": 1,
    "fastfilling": 0,
    "housefull": 0,
    "occupancy": 0.43
  },
  "Avatar: Fire and Ash [MX4D 3D | Hindi]": {
    "shows": 2,
    "gross": 9780.0,
    "sold": 22,
    "totalSeats": 200,
    "venues": 1,
    "cities": 1,
    "fastfilling": 0,
    "housefull": 0,
    "occupancy": 11.0
  },
  "The Housemaid [2D | English]": {
    "shows": 2,
    "gross": 44590.0,
    "sold": 89,
    "totalSeats": 234,
    "venues": 2,
    "cities": 1,
    "fastfilling": 0,
    "housefull": 0,
    "occupancy": 38.03
  },
  "Zootopia 2 [3D | English]": {
    "shows": 11,
    "gross": 54745.0,
    "sold": 150,
    "totalSeats": 1302,
    "venues": 5,
    "cities": 1,
    "fastfilling": 0,
    "housefull": 0,
    "occupancy": 11.52
  },
  "Valavaara [2D | Kannada]": {
    "shows": 7,
    "gross": 46360.0,
    "sold": 265,
    "totalSeats": 2052,
    "venues": 7,
    "cities": 2,
    "fastfilling": 0,
    "housefull": 0,
    "occupancy": 12.91
  },
  "Seat Edge [2D | Kannada]": {
    "shows": 9,
    "gross": 51550.0,
    "sold": 343,
    "totalSeats": 1900,
    "venues": 8,
    "cities": 2,
    "fastfilling": 1,
    "housefull": 0,
    "occupancy": 18.05
  },
  "Bhanupriya Bhooter Hotel [2D | Bengali]": {
    "shows": 5,
    "gross": 2850.0,
    "sold": 13,
    "totalSeats": 401,
    "venues": 4,
    "cities": 4,
    "fastfilling": 0,
    "housefull": 0,
    "occupancy": 3.24
  },
  "Malumadi [2D | Gujarati]": {
    "shows": 5,
    "gross": 7980.0,
    "sold": 48,
    "totalSeats": 545,
    "venues": 5,
    "cities": 4,
    "fastfilling": 0,
    "housefull": 0,
    "occupancy": 8.81
  },
  "Khabar Naahe [2D | Sindhi]": {
    "shows": 1,
    "gross": 17360.0,
    "sold": 124,
    "totalSeats": 124,
    "venues": 1,
    "cities": 1,
    "fastfilling": 0,
    "housefull": 1,
    "occupancy": 100.0
  },
  "Parasakthi [2D | Tamil]": {
    "shows": 3,
    "gross": 13766.6,
    "sold": 109,
    "totalSeats": 1139,
    "venues": 2,
    "cities": 2,
    "fastfilling": 0,
    "housefull": 0,
    "occupancy": 9.57
  },
  "Laalo - Krishna Sada Sahaayate [2D | Gujarati]": {
    "shows": 2,
    "gross": 3300.0,
    "sold": 23,
    "totalSeats": 300,
    "venues": 2,
    "cities": 1,
    "fastfilling": 0,
    "housefull": 0,
    "occupancy": 7.67
  },
  "Pazhuthu [2D | Malayalam]": {
    "shows": 1,
    "gross": 1050.0,
    "sold": 10,
    "totalSeats": 70,
    "venues": 1,
    "cities": 1,
    "fastfilling": 0,
    "housefull": 0,
    "occupancy": 14.29
  },
  "Dhrutarashtrudu [2D | Telugu]": {
    "shows": 2,
    "gross": 0.0,
    "sold": 0,
    "totalSeats": 488,
    "venues": 1,
    "cities": 1,
    "fastfilling": 0,
    "housefull": 0,
    "occupancy": 0.0
  },
  "Avatar: Fire and Ash [IMAX 3D | English]": {
    "shows": 1,
    "gross": 12800.0,
    "sold": 25,
    "totalSeats": 275,
    "venues": 1,
    "cities": 1,
    "fastfilling": 0,
    "housefull": 0,
    "occupancy": 9.09
  },
  "Private Teacher [2D | Hindi]": {
    "shows": 3,
    "gross": 1050.0,
    "sold": 15,
    "totalSeats": 750,
    "venues": 1,
    "cities": 1,
    "fastfilling": 0,
    "housefull": 0,
    "occupancy": 2.0
  },
  "Happy Patel: Khatarnak Jasoos [2D | Hindi]": {
    "shows": 1,
    "gross": 10880.0,
    "sold": 35,
    "totalSeats": 178,
    "venues": 1,
    "cities": 1,
    "fastfilling": 0,
    "housefull": 0,
    "occupancy": 19.66
  },
  "Mercy [3D | English]": {
    "shows": 2,
    "gross": 7650.0,
    "sold": 15,
    "totalSeats": 176,
    "venues": 2,
    "cities": 1,
    "fastfilling": 0,
    "housefull": 0,
    "occupancy": 8.52
  },
  "Kaavalan [2D | Tamil]": {
    "shows": 16,
    "gross": 72440.0,
    "sold": 534,
    "totalSeats": 12067,
    "venues": 10,
    "cities": 1,
    "fastfilling": 0,
    "housefull": 0,
    "occupancy": 4.43
  },
  "Rickshawkaran [2D | Tamil]": {
    "shows": 1,
    "gross": 2460.0,
    "sold": 20,
    "totalSeats": 897,
    "venues": 1,
    "cities": 1,
    "fastfilling": 0,
    "housefull": 0,
    "occupancy": 2.23
  },
  "Jai Kanhaiyalall Ki [2D | Gujarati]": {
    "shows": 1,
    "gross": 2430.0,
    "sold": 18,
    "totalSeats": 125,
    "venues": 1,
    "cities": 1,
    "fastfilling": 0,
    "housefull": 0,
    "occupancy": 14.4
  },
  "Avatar: Fire and Ash [3D | Hindi]": {
    "shows": 2,
    "gross": 3290.0,
    "sold": 12,
    "totalSeats": 266,
    "venues": 2,
    "cities": 1,
    "fastfilling": 0,
    "housefull": 0,
    "occupancy": 4.51
  },
  "Ikkis [2D | Hindi]": {
    "shows": 1,
    "gross": 26400.0,
    "sold": 264,
    "totalSeats": 275,
    "venues": 1,
    "cities": 1,
    "fastfilling": 1,
    "housefull": 0,
    "occupancy": 96.0
  },
  "Projapati 2 [2D | Bengali]": {
    "shows": 3,
    "gross": 1460.0,
    "sold": 12,
    "totalSeats": 445,
    "venues": 3,
    "cities": 2,
    "fastfilling": 0,
    "housefull": 0,
    "occupancy": 2.7
  },
  "Krantijyoti Vidyalay Marathi Madhyam [2D | Marathi]": {
    "shows": 1,
    "gross": 1800.0,
    "sold": 12,
    "totalSeats": 193,
    "venues": 1,
    "cities": 1,
    "fastfilling": 0,
    "housefull": 0,
    "occupancy": 6.22
  },
  "Sirai [2D | Tamil]": {
    "shows": 1,
    "gross": 2891.4,
    "sold": 27,
    "totalSeats": 97,
    "venues": 1,
    "cities": 1,
    "fastfilling": 0,
    "housefull": 0,
    "occupancy": 27.84
  },
  "Howddo Huliya [2D | Kannada]": {
    "shows": 1,
    "gross": 28290.0,
    "sold": 149,
    "totalSeats": 195,
    "venues": 1,
    "cities": 1,
    "fastfilling": 1,
    "housefull": 0,
    "occupancy": 76.41
  },
  "Rahu Ketu [2D | Hindi]": {
    "shows": 1,
    "gross": 0.0,
    "sold": 0,
    "totalSeats": 209,
    "venues": 1,
    "cities": 1,
    "fastfilling": 0,
    "housefull": 0,
    "occupancy": 0.0
  },
  "Paree: An Unsolved Mystery [2D | Odia]": {
    "shows": 3,
    "gross": 440.0,
    "sold": 2,
    "totalSeats": 415,
    "venues": 3,
    "cities": 3,
    "fastfilling": 0,
    "housefull": 0,
    "occupancy": 0.48
  },
  "Hok Kolorob [2D | Bengali]": {
    "shows": 1,
    "gross": 360.0,
    "sold": 3,
    "totalSeats": 88,
    "venues": 1,
    "cities": 1,
    "fastfilling": 0,
    "housefull": 0,
    "occupancy": 3.41
  },
  "Bose [2D | Kannada]": {
    "shows": 1,
    "gross": 8580.0,
    "sold": 39,
    "totalSeats": 265,
    "venues": 1,
    "cities": 1,
    "fastfilling": 0,
    "housefull": 0,
    "occupancy": 14.72
  },
  "Zootopia 2 [2D | Hindi]": {
    "shows": 1,
    "gross": 23500.0,
    "sold": 235,
    "totalSeats": 235,
    "venues": 1,
    "cities": 1,
    "fastfilling": 0,
    "housefull": 1,
    "occupancy": 100.0
  },
  "Avatar: Fire and Ash [2D | Hindi]": {
    "shows": 1,
    "gross": 0.0,
    "sold": 0,
    "totalSeats": 199,
    "venues": 1,
    "cities": 1,
    "fastfilling": 0,
    "housefull": 0,
    "occupancy": 0.0
  },
  "Sagwaan [2D | Hindi]": {
    "shows": 1,
    "gross": 4000.0,
    "sold": 40,
    "totalSeats": 166,
    "venues": 1,
    "cities": 1,
    "fastfilling": 0,
    "housefull": 0,
    "occupancy": 24.1
  }
}